nfldfs/__init__.py
nfldfs/games.py
nfldfs/utils.py
nfldfs-0.0.5.dist-info/LICENSE
nfldfs-0.0.5.dist-info/METADATA
nfldfs-0.0.5.dist-info/WHEEL
nfldfs-0.0.5.dist-info/entry_points.txt
nfldfs-0.0.5.dist-info/top_level.txt
nfldfs-0.0.5.dist-info/RECORD
