Metadata-Version: 2.1
Name: nfldfs
Version: 0.0.5
Summary: A simple package to scrape NFL daily fantasy data.
Home-page: https://github.com/briandoucet01/nfldfs
Author: Brian Doucet
Author-email: doucetba@gmail.com
License: MIT
Keywords: nfl daily fantasy sports dfs sports analytics draftkings fanduel yahoo
Platform: UNKNOWN
Classifier: License :: OSI Approved :: MIT License
Classifier: Programming Language :: Python :: 3
Classifier: Topic :: Software Development :: Libraries
Requires-Python: >=3.0
Requires-Dist: beautifulsoup4 (==4.8.2)
Requires-Dist: click (==7.1.1)
Requires-Dist: lxml (==4.5.0)
Requires-Dist: pandas (==1.0.3)
Requires-Dist: requests (==2.23.0)
